pymakeself/__init__.py
pymakeself/__main__.py
pymakeself/installhosts.py
pymakeself/makeself.py
pymakeself/aes/__init__.py
pymakeself/aes/aesctr.py
pymakeself/aes/aesutil.py
pymakeself/installtools/__init__.py
pymakeself/installtools/accountutil.py
pymakeself-0.4.0.dist-info/LICENSE
pymakeself-0.4.0.dist-info/METADATA
pymakeself-0.4.0.dist-info/WHEEL
pymakeself-0.4.0.dist-info/entry_points.txt
pymakeself-0.4.0.dist-info/top_level.txt
pymakeself-0.4.0.dist-info/RECORD
