Metadata-Version: 2.1
Name: pymakeself
Version: 0.4.0
Summary: pymakeself: make self-extracting archives
Home-page: https://github.com/gammazero/pymakeself
Author: Andrew Gillis
Author-email: gillis.andrewj@gmail.com
License: http://www.opensource.org/licenses/mit-license.php
Keywords: archive installation tar
Platform: unix
Platform: linux
Platform: osx
Platform: cygwin
Platform: win32
Classifier: Development Status :: 5 - Production/Stable
Classifier: Intended Audience :: Developers
Classifier: License :: OSI Approved :: MIT License
Classifier: Operating System :: POSIX
Classifier: Operating System :: MacOS :: MacOS X
Classifier: Operating System :: Microsoft :: Windows
Classifier: Topic :: Software Development :: Libraries
Classifier: Topic :: Utilities
Classifier: Programming Language :: Python
Classifier: Programming Language :: Python :: 3
License-File: LICENSE
